maktabkhooneh_downloader/__init__.py
maktabkhooneh_downloader/__main__.py
maktabkhooneh_downloader/auth/__init__.py
maktabkhooneh_downloader/auth/browsers.py
maktabkhooneh_downloader/auth/login.py
maktabkhooneh_downloader/download/downloader.py
maktabkhooneh_downloader/menus.py
mkdl-1.0.0b1.dist-info/entry_points.txt
mkdl-1.0.0b1.dist-info/LICENSE
mkdl-1.0.0b1.dist-info/METADATA
mkdl-1.0.0b1.dist-info/WHEEL
mkdl-1.0.0b1.dist-info/RECORD
