Metadata-Version: 2.3
Name: mkdl
Version: 1.0.0b1
Summary: Effortlessly download Maktabkhooneh.org courses with speed and smart features
Author: hesam21188
Author-email: hosseinharatii@gmail.com
Requires-Python: >=3.11,<4.0
Classifier: Programming Language :: Python :: 3
Classifier: Programming Language :: Python :: 3.11
Classifier: Programming Language :: Python :: 3.12
Classifier: Programming Language :: Python :: 3.13
Requires-Dist: InquirerPy (>=0.3.4,<0.4.0)
Requires-Dist: beautifulsoup4 (>=4.12.0,<5.0.0)
Requires-Dist: browser-cookie3 (>=0.20.0,<0.21.0)
Requires-Dist: requests (>=2.31.0,<3.0.0)
Requires-Dist: rich (>=13.7.0,<14.0.0)
Requires-Dist: typer[all] (>=0.9.0,<0.10.0)
